README.md
setup.cfg
setup.py
modelevaluationammh/__init__.py
modelevaluationammh/modelevaluationammh.py
modelevaluationammh.egg-info/PKG-INFO
modelevaluationammh.egg-info/SOURCES.txt
modelevaluationammh.egg-info/dependency_links.txt
modelevaluationammh.egg-info/not-zip-safe
modelevaluationammh.egg-info/requires.txt
modelevaluationammh.egg-info/top_level.txt