Metadata-Version: 1.0
Name: modelevaluationammh
Version: 0.2.2
Summary: Model Evaluation tools
Home-page: UNKNOWN
Author: Alder Martinez & Michael Howard
Author-email: aldermartinez@gmail.com
License: MIT
Platform: UNKNOWN
